Metadata-Version: 2.1
Name: haaahhaha
Version: 0.1
Summary: cantdoitanymorehaahahaaha
